README.md
setup.py
trStr/__init__.py
trStr/trStr.py
trStr.egg-info/PKG-INFO
trStr.egg-info/SOURCES.txt
trStr.egg-info/dependency_links.txt
trStr.egg-info/top_level.txt