Metadata-Version: 2.1
Name: trStr
Version: 1.0.4
Summary: String methods for Turkish characters
Home-page: https://seridilekce.com
Author: Muhammet Fatih DİNÇ
Author-email: mfatihdinc61@gmail.com
License: MIT
Keywords: turkish,string,upper
Classifier: Development Status :: 3 - Alpha
Classifier: Intended Audience :: Developers
Classifier: Topic :: Software Development :: Build Tools
Classifier: License :: OSI Approved :: MIT License
Classifier: Programming Language :: Python :: 3.5
Classifier: Programming Language :: Python :: 3.6
Classifier: Programming Language :: Python :: 3.7
Classifier: Programming Language :: Python :: 3.8
Classifier: Programming Language :: Python :: 3.9
Classifier: Programming Language :: Python :: 3.10
